odoo/addons/partner_aging/README.rst
odoo/addons/partner_aging/__init__.py
odoo/addons/partner_aging/__manifest__.py
odoo/addons/partner_aging/i18n/partner_aging.pot
odoo/addons/partner_aging/i18n/pt.po
odoo/addons/partner_aging/readme/CONTRIBUTORS.rst
odoo/addons/partner_aging/readme/DESCRIPTION.rst
odoo/addons/partner_aging/readme/USAGE.rst
odoo/addons/partner_aging/security/ir.model.access.csv
odoo/addons/partner_aging/static/description/icon.png
odoo/addons/partner_aging/static/description/index.html
odoo/addons/partner_aging/tests/__init__.py
odoo/addons/partner_aging/tests/test_partner_aging.py
odoo/addons/partner_aging/wizards/__init__.py
odoo/addons/partner_aging/wizards/res_partner_aging_customer.py
odoo/addons/partner_aging/wizards/res_partner_aging_customer.xml
odoo/addons/partner_aging/wizards/res_partner_aging_date.py
odoo/addons/partner_aging/wizards/res_partner_aging_supplier.py
odoo/addons/partner_aging/wizards/res_partner_aging_supplier.xml
odoo11_addon_partner_aging-11.0.1.0.0.99.dev4.dist-info/METADATA
odoo11_addon_partner_aging-11.0.1.0.0.99.dev4.dist-info/WHEEL
odoo11_addon_partner_aging-11.0.1.0.0.99.dev4.dist-info/top_level.txt
odoo11_addon_partner_aging-11.0.1.0.0.99.dev4.dist-info/RECORD
